django_random_id.py
django_random_id-0.1.0.dist-info/LICENSE
django_random_id-0.1.0.dist-info/METADATA
django_random_id-0.1.0.dist-info/WHEEL
django_random_id-0.1.0.dist-info/top_level.txt
django_random_id-0.1.0.dist-info/RECORD
