Metadata-Version: 2.1
Name: django-random-id
Version: 0.1.0
Summary: A model base class which provides custom designed random integer primary keys to you Django models.
Author: Serdar Ilarslan
License: MIT
Keywords: django orm primary-key
Classifier: Development Status :: 5 - Production/Stable
Classifier: Operating System :: OS Independent
Classifier: Intended Audience :: Developers
Classifier: License :: OSI Approved :: MIT License
Classifier: Topic :: Software Development :: Libraries
Classifier: Framework :: Django
Classifier: Programming Language :: Python :: 3
Classifier: Programming Language :: Python :: 3.6
Classifier: Programming Language :: Python :: 3.7
Classifier: Programming Language :: Python :: 3.8
Classifier: Programming Language :: Python :: 3.9
License-File: LICENSE
Requires-Dist: django >=3.0
Provides-Extra: dev
Requires-Dist: django >=3.0 ; extra == 'dev'
Requires-Dist: pytest ; extra == 'dev'
